odltools/__init__.py
odltools/__main__.py
odltools/cli.py
odltools/cli_utils.py
odltools/logg.py
odltools/bist/__init__.py
odltools/bist/cli.py
odltools/bist/diagnostics/__init__.py
odltools/bist/diagnostics/base.py
odltools/bist/tests/__init__.py
odltools/bist/tests/diagnostic/README.rst
odltools/bist/tests/diagnostic/__init__.py
odltools/bist/tests/unit/__init__.py
odltools/bist/tests/unit/test_cli.py
odltools/bist/tests/unit/diagnostics/__init__.py
odltools/bist/tests/unit/diagnostics/test_base.py
odltools/common/__init__.py
odltools/common/files.py
odltools/common/rest_client.py
odltools/common/ssh.py
odltools/common/tests/__init__.py
odltools/common/tests/test_files.py
odltools/common/tests/test_rest_client.py
odltools/csit/__init__.py
odltools/csit/cli.py
odltools/csit/robotfiles.py
odltools/csit/reports/__init__.py
odltools/csit/reports/console.py
odltools/csit/reports/excepts.py
odltools/csit/reports/reports.py
odltools/csit/tests/__init__.py
odltools/csit/tests/test_reports.py
odltools/csit/tests/test_reports_console.py
odltools/csit/tests/test_reports_excepts.py
odltools/csit/tests/test_robotfiles.py
odltools/flows/__init__.py
odltools/flows/cli.py
odltools/flows/flow.py
odltools/flows/odl_flows.py
odltools/flows/ovs_flows.py
odltools/flows/tests/__init__.py
odltools/flows/tests/test_cli.py
odltools/flows/tests/test_ovs_flows.py
odltools/karaf/__init__.py
odltools/karaf/cli.py
odltools/karaf/dump.py
odltools/mdsal/__init__.py
odltools/mdsal/cli.py
odltools/mdsal/models/Modules.py
odltools/mdsal/models/__init__.py
odltools/mdsal/models/constants.py
odltools/mdsal/models/elan.py
odltools/mdsal/models/entity_owners.py
odltools/mdsal/models/id_manager.py
odltools/mdsal/models/ietf_interfaces.py
odltools/mdsal/models/interface_service_bindings.py
odltools/mdsal/models/itm.py
odltools/mdsal/models/itm_state.py
odltools/mdsal/models/l3vpn.py
odltools/mdsal/models/mip.py
odltools/mdsal/models/model.py
odltools/mdsal/models/models.py
odltools-0.1.34.dist-info/AUTHORS
odltools-0.1.34.dist-info/LICENSE
odltools-0.1.34.dist-info/METADATA
odltools-0.1.34.dist-info/WHEEL
odltools-0.1.34.dist-info/entry_points.txt
odltools-0.1.34.dist-info/pbr.json
odltools-0.1.34.dist-info/top_level.txt
odltools-0.1.34.dist-info/RECORD
